finrashortdata/__init__.py
finrashortdata/auth.py
finrashortdata/daily.py
finrashortdata/decorators.py
finrashortdata-0.1.1.data/data/finrashortdata/release.txt
finrashortdata-0.1.1.dist-info/LICENSE
finrashortdata-0.1.1.dist-info/METADATA
finrashortdata-0.1.1.dist-info/WHEEL
finrashortdata-0.1.1.dist-info/top_level.txt
finrashortdata-0.1.1.dist-info/RECORD
