Metadata-Version: 2.1
Name: finrashortdata
Version: 0.1.1
Summary: Process FINRA Short Daily Data feeds
Home-page: https://github.com/amor71/FINRAShortData
Author: amor71
Author-email: amor71@sgeltd.com
License: GNU GPL v3.0
Classifier: Programming Language :: Python :: 3.9
Classifier: Programming Language :: Python :: 3.10
Classifier: License :: OSI Approved :: MIT License
Classifier: Operating System :: OS Independent
Requires-Python: >=3.9
License-File: LICENSE
Requires-Dist: requests
Requires-Dist: pandas
Requires-Dist: pandas-market-calendars
